ikehTobrut/__init__.py
ikehtobrut-0.1.1.dist-info/licenses/LICENSE
ikehtobrut-0.1.1.dist-info/METADATA
ikehtobrut-0.1.1.dist-info/WHEEL
ikehtobrut-0.1.1.dist-info/top_level.txt
ikehtobrut-0.1.1.dist-info/RECORD
